{"name":"build-javascript","namedChunkGroups":{"app":{"name":"app","assets":[{"name":"webpack-runtime-deaf914629d1a9320a8d.js","size":3858},{"name":"framework-6a525285796fb83f2864.js","size":140785},{"name":"styles.9e907bc32054b7771552.css","size":1245},{"name":"app-26b3a1604ebc861d3567.js","size":82773}],"filteredAssets":0,"assetsSize":228661,"filteredAuxiliaryAssets":3,"auxiliaryAssetsSize":725708},"component---src-pages-index-tsx":{"name":"component---src-pages-index-tsx","assets":[{"name":"c16184b3-346cf6eadf1e397b427d.js","size":831},{"name":"2cca2479-b49a0fcde0709662d595.js","size":1960},{"name":"6cd7a83d-11c51c036b79cb2ae581.js","size":28006},{"name":"component---src-pages-index-tsx-36580d5839c39d16c918.js","size":152852}],"filteredAssets":0,"assetsSize":183649,"filteredAuxiliaryAssets":22,"auxiliaryAssetsSize":11940402}},"assetsByChunkName":{"app":["webpack-runtime-deaf914629d1a9320a8d.js","framework-6a525285796fb83f2864.js","styles.9e907bc32054b7771552.css","app-26b3a1604ebc861d3567.js"],"component---src-pages-index-tsx":["c16184b3-346cf6eadf1e397b427d.js","2cca2479-b49a0fcde0709662d595.js","6cd7a83d-11c51c036b79cb2ae581.js","component---src-pages-index-tsx-36580d5839c39d16c918.js"]},"childAssetsByChunkName":{}}